MANIFEST.in
README.md
requirements.txt
setup.py
./driftage/__init__.py
./driftage/__pycache__/__init__.cpython-37.pyc
./driftage/analyser/__init__.py
./driftage/analyser/predictor.py
./driftage/analyser/__pycache__/__init__.cpython-37.pyc
./driftage/analyser/__pycache__/predictor.cpython-37.pyc
./driftage/analyser/behaviour/__init__.py
./driftage/analyser/behaviour/receive_new_data.py
./driftage/analyser/behaviour/store_new_data.py
./driftage/analyser/behaviour/train_predictor.py
./driftage/analyser/behaviour/__pycache__/__init__.cpython-37.pyc
./driftage/analyser/behaviour/__pycache__/receive_new_data.cpython-37.pyc
./driftage/analyser/behaviour/__pycache__/store_new_data.cpython-37.pyc
./driftage/analyser/behaviour/__pycache__/train_predictor.cpython-37.pyc
./driftage/base/__init__.py
./driftage/base/conf.py
./driftage/base/predictor.py
./driftage/base/__pycache__/__init__.cpython-37.pyc
./driftage/base/__pycache__/conf.cpython-37.pyc
./driftage/base/__pycache__/predictor.cpython-37.pyc
./driftage/base/agent/__init__.py
./driftage/base/agent/subscriptor.py
./driftage/base/agent/__pycache__/__init__.cpython-37.pyc
./driftage/base/agent/__pycache__/subscriptor.cpython-37.pyc
./driftage/base/behaviour/__init__.py
./driftage/base/behaviour/wait_subscriptions.py
./driftage/base/behaviour/__pycache__/__init__.cpython-37.pyc
./driftage/base/behaviour/__pycache__/wait_subscriptions.cpython-37.pyc
./driftage/db/__init__.py
./driftage/db/connection.py
./driftage/db/schema.py
./driftage/db/__pycache__/__init__.cpython-37.pyc
./driftage/db/__pycache__/connection.cpython-37.pyc
./driftage/db/__pycache__/schema.cpython-37.pyc
./driftage/executor/__init__.py
./driftage/executor/retry_config.py
./driftage/executor/sink.py
./driftage/executor/__pycache__/__init__.cpython-37.pyc
./driftage/executor/__pycache__/retry_config.cpython-37.pyc
./driftage/executor/__pycache__/sink.cpython-37.pyc
./driftage/executor/behaviour/__init__.py
./driftage/executor/behaviour/receive_new_data.py
driftage.egg-info/PKG-INFO
driftage.egg-info/SOURCES.txt
driftage.egg-info/dependency_links.txt
driftage.egg-info/requires.txt
driftage.egg-info/top_level.txt
