Metadata-Version: 2.1
Name: driftage
Version: 0.0.9
Summary: Multi-agent Drift Detection Platform
Home-page: https://github.com/dmvieira/driftage
Author: Diogo Munaro Vieira
Author-email: diogo.mvieira@gmail.com
License: Apache 2
Platform: UNKNOWN
Classifier: Programming Language :: Python :: 3
Classifier: License :: OSI Approved :: Apache Software License
Classifier: Topic :: Software Development :: Libraries :: Python Modules
Classifier: Topic :: Software Development :: Libraries :: Application Frameworks
